Workbook

Sheet Criteria & Weights
A1: HVMC Multi-Criteria Risk Evaluation — Criteria and Weights
A2: Version 1.0 · October 14, 2026 · Weights derived by AHP pairwise comparison (yellow = inputs)
A4: Pairwise comparison (row vs column, Saaty 1–9 scale)
A5: Factor | B5: Financial | C5: Operational | D5: Compliance | E5: Reputation | F5: Geometric mean | G5: Weight (exact) | H5: Weight (used)
A6: Financial | B6: 1 | C6: 0.5 | D6: 0.5 | E6: 2 | F6: =(B6*C6*D6*E6)^(1/4) | G6: =F6/SUM($F$6:$F$9) | H6: 0.19
A7: Operational | B7: 2 | C7: 1 | D7: 1 | E7: 3 | F7: =(B7*C7*D7*E7)^(1/4) | G7: =F7/SUM($F$6:$F$9) | H7: 0.36
A8: Compliance | B8: 2 | C8: 1 | D8: 1 | E8: 2 | F8: =(B8*C8*D8*E8)^(1/4) | G8: =F8/SUM($F$6:$F$9) | H8: 0.33
A9: Reputation | B9: 0.5 | C9: 0.33333333 | D9: 0.5 | E9: 1 | F9: =(B9*C9*D9*E9)^(1/4) | G9: =F9/SUM($F$6:$F$9) | H9: 0.12
A10: Total | G10: =SUM(G6:G9) | H10: =SUM(H6:H9)
A12: λmax | B12: 4.0457
A13: Consistency index CI = (λmax − n)/(n − 1) | B13: =(B12-4)/3
A14: Random index RI (n = 4) | B14: 0.9
A15: Consistency ratio CR = CI/RI (must be < 0.10) | B15: =B13/B14 | C15: =IF(B15<0.1,"Consistent ✓","Revise comparisons")
A17: Measurement scales (score 1–5)
A18: Score | B18: Financial | C18: Operational | D18: Compliance | E18: Reputation
A19: 1 | B19: < $10K | C19: No service impact | D19: No regulatory issue | E19: No external awareness
A20: 2 | B20: $10K – $100K | C20: Non-clinical service degraded < 4 h | D20: Internal policy breach only | E20: Individual patient complaints
A21: 3 | B21: $100K – $500K | C21: Clinical workflow on downtime procedures < 24 h | D21: HIPAA violation < 500 records (annual HHS log) | E21: Local media coverage
A22: 4 | B22: $500K – $2M | C22: Clinical system down 1–3 days, or temporary patient harm possible | D22: Reportable breach ≥ 500 records; OCR investigation | E22: Regional media; measurable patient attrition
A23: 5 | B23: > $2M | C23: Clinical system down > 3 days, or serious patient harm | D23: OCR Tier 3–4 penalty / corrective action plan; state AG action | E23: National media; lasting loss of trust
A25: Rules
A26: 1. Weighted impact WI = Σ (weight × factor score), range 1–5
A27: 2. Weighted risk score = Likelihood (1–5) × WI, range 1–25
A28: 3. Bands: Critical ≥ 20 · High 12–19.99 · Medium 6–11.99 · Low < 6
A29: 4. Critical-factor floor: any factor = 5 with Likelihood ≥ 3 → rating at least High
A30: 5. Patient safety is scored inside Operational; Operational = 5 always escalates to the Security & Risk Lead

Sheet Weighted Scoring
A1: Multi-Criteria Weighted Risk Scores
A2: Factor scores are inputs; WI, score and rating are formulas linked to Criteria & Weights!H6:H9
A4: ID | B4: Risk | C4: Likelihood | D4: Financial | E4: Operational | F4: Compliance | G4: Reputation | H4: Weighted impact | I4: Weighted score | J4: Base rating | K4: Floor rule? | L4: Final rating | M4: Previous 5×5 score | N4: Rank (previous) | O4: Rank (weighted) | P4: Scoring rationale | Q4: Owner
A5: R01 | B5: Security incident goes undetected for months (no central logging or alerting) | C5: 4 | D5: 5 | E5: 3 | F5: 5 | G5: 4 | H5: =D5*'Criteria & Weights'!$H$6+E5*'Criteria & Weights'!$H$7+F5*'Criteria & Weights'!$H$8+G5*'Criteria & Weights'!$H$9 | I5: =C5*H5 | J5: =IF(I5>=20,"Critical",IF(I5>=12,"High",IF(I5>=6,"Medium","Low"))) | K5: =IF(AND(MAX(D5:G5)=5,C5>=3,OR(J5="Low",J5="Medium")),"Yes","") | L5: =IF(K5="Yes","High",J5) | M5: 20 | N5: 1 | O5: =RANK(I5,$I$5:$I$20) | P5: Undetected breach multiplies cost; HIPAA audit-control failure; delayed disclosure draws media | Q5: Fatima Ali
A6: R05 | B6: Ransomware or malicious deletion destroys EHR data | C6: 3 | D6: 5 | E6: 5 | F6: 4 | G6: 5 | H6: =D6*'Criteria & Weights'!$H$6+E6*'Criteria & Weights'!$H$7+F6*'Criteria & Weights'!$H$8+G6*'Criteria & Weights'!$H$9 | I6: =C6*H6 | J6: =IF(I6>=20,"Critical",IF(I6>=12,"High",IF(I6>=6,"Medium","Low"))) | K6: =IF(AND(MAX(D6:G6)=5,C6>=3,OR(J6="Low",J6="Medium")),"Yes","") | L6: =IF(K6="Yes","High",J6) | M6: 15 | N6: 5 | O6: =RANK(I6,$I$5:$I$20) | P6: Multi-day EHR outage, ambulance diversion, unrecoverable records | Q6: Fatima Ali
A7: R03 | B7: Lateral movement from Web tier to Data tier | C7: 3 | D7: 5 | E7: 4 | F7: 5 | G7: 4 | H7: =D7*'Criteria & Weights'!$H$6+E7*'Criteria & Weights'!$H$7+F7*'Criteria & Weights'!$H$8+G7*'Criteria & Weights'!$H$9 | I7: =C7*H7 | J7: =IF(I7>=20,"Critical",IF(I7>=12,"High",IF(I7>=6,"Medium","Low"))) | K7: =IF(AND(MAX(D7:G7)=5,C7>=3,OR(J7="Low",J7="Medium")),"Yes","") | L7: =IF(K7="Yes","High",J7) | M7: 15 | N7: 4 | O7: =RANK(I7,$I$5:$I$20) | P7: Database compromise allows ePHI theft and dose/result tampering (patient safety) | Q7: Fatima Ali
A8: R10 | B8: Remote code execution via Apache 2.4.7 mod_lua (CVE-2021-44790, CVSS 9.8) | C8: 4 | D8: 4 | E8: 3 | F8: 3 | G8: 3 | H8: =D8*'Criteria & Weights'!$H$6+E8*'Criteria & Weights'!$H$7+F8*'Criteria & Weights'!$H$8+G8*'Criteria & Weights'!$H$9 | I8: =C8*H8 | J8: =IF(I8>=20,"Critical",IF(I8>=12,"High",IF(I8>=6,"Medium","Low"))) | K8: =IF(AND(MAX(D8:G8)=5,C8>=3,OR(J8="Low",J8="Medium")),"Yes","") | L8: =IF(K8="Yes","High",J8) | M8: 20 | N8: 2 | O8: =RANK(I8,$I$5:$I$20) | P8: Public web server compromise; legacy lab target, no ePHI stored | Q8: Kevin O'Brien
A9: R02 | B9: ePHI exfiltration from EHR storage over the public internet | C9: 3 | D9: 5 | E9: 2 | F9: 5 | G9: 5 | H9: =D9*'Criteria & Weights'!$H$6+E9*'Criteria & Weights'!$H$7+F9*'Criteria & Weights'!$H$8+G9*'Criteria & Weights'!$H$9 | I9: =C9*H9 | J9: =IF(I9>=20,"Critical",IF(I9>=12,"High",IF(I9>=6,"Medium","Low"))) | K9: =IF(AND(MAX(D9:G9)=5,C9>=3,OR(J9="Low",J9="Medium")),"Yes","") | L9: =IF(K9="Yes","High",J9) | M9: 15 | N9: 3 | O9: =RANK(I9,$I$5:$I$20) | P9: Bulk ePHI exposure: breach cost + OCR investigation + national coverage; EHR keeps running | Q9: Fatima Ali
A10: R11 | B10: Malware uploaded to EHR storage is not detected | C10: 3 | D10: 3 | E10: 4 | F10: 3 | G10: 3 | H10: =D10*'Criteria & Weights'!$H$6+E10*'Criteria & Weights'!$H$7+F10*'Criteria & Weights'!$H$8+G10*'Criteria & Weights'!$H$9 | I10: =C10*H10 | J10: =IF(I10>=20,"Critical",IF(I10>=12,"High",IF(I10>=6,"Medium","Low"))) | K10: =IF(AND(MAX(D10:G10)=5,C10>=3,OR(J10="Low",J10="Medium")),"Yes","") | L10: =IF(K10="Yes","High",J10) | M10: 12 | N10: 9 | O10: =RANK(I10,$I$5:$I$20) | P10: Malware spreads to clinical workstations; downtime procedures needed | Q10: Denise Coleman
A11: R04 | B11: Loss or takeover of the only Global Administrator account | C11: 3 | D11: 3 | E11: 4 | F11: 3 | G11: 2 | H11: =D11*'Criteria & Weights'!$H$6+E11*'Criteria & Weights'!$H$7+F11*'Criteria & Weights'!$H$8+G11*'Criteria & Weights'!$H$9 | I11: =C11*H11 | J11: =IF(I11>=20,"Critical",IF(I11>=12,"High",IF(I11>=6,"Medium","Low"))) | K11: =IF(AND(MAX(D11:G11)=5,C11>=3,OR(J11="Low",J11="Medium")),"Yes","") | L11: =IF(K11="Yes","High",J11) | M11: 12 | N11: 7 | O11: =RANK(I11,$I$5:$I$20) | P11: Admin lockout halts recovery and change for days; limited direct data exposure | Q11: Sabitha S Karanavar
A12: R09 | B12: Remote code execution via OpenSSH 6.6.1p1 (CVE-2023-38408, CVSS 9.8) | C12: 3 | D12: 4 | E12: 3 | F12: 3 | G12: 3 | H12: =D12*'Criteria & Weights'!$H$6+E12*'Criteria & Weights'!$H$7+F12*'Criteria & Weights'!$H$8+G12*'Criteria & Weights'!$H$9 | I12: =C12*H12 | J12: =IF(I12>=20,"Critical",IF(I12>=12,"High",IF(I12>=6,"Medium","Low"))) | K12: =IF(AND(MAX(D12:G12)=5,C12>=3,OR(J12="Low",J12="Medium")),"Yes","") | L12: =IF(K12="Yes","High",J12) | M12: 15 | N12: 6 | O12: =RANK(I12,$I$5:$I$20) | P12: Host takeover; legacy lab target, no ePHI stored | Q12: Kevin O'Brien
A13: R08 | B13: Consent phishing or rogue app via open tenant settings | C13: 3 | D13: 3 | E13: 2 | F13: 4 | G13: 3 | H13: =D13*'Criteria & Weights'!$H$6+E13*'Criteria & Weights'!$H$7+F13*'Criteria & Weights'!$H$8+G13*'Criteria & Weights'!$H$9 | I13: =C13*H13 | J13: =IF(I13>=20,"Critical",IF(I13>=12,"High",IF(I13>=6,"Medium","Low"))) | K13: =IF(AND(MAX(D13:G13)=5,C13>=3,OR(J13="Low",J13="Medium")),"Yes","") | L13: =IF(K13="Yes","High",J13) | M13: 12 | N13: 8 | O13: =RANK(I13,$I$5:$I$20) | P13: Malicious app reads user data; OCR-reportable if PHI involved | Q13: Sabitha S Karanavar
A14: R12 | B14: Clinician credentials stolen by MFA-bypass (AiTM) phishing | C14: 3 | D14: 3 | E14: 2 | F14: 4 | G14: 3 | H14: =D14*'Criteria & Weights'!$H$6+E14*'Criteria & Weights'!$H$7+F14*'Criteria & Weights'!$H$8+G14*'Criteria & Weights'!$H$9 | I14: =C14*H14 | J14: =IF(I14>=20,"Critical",IF(I14>=12,"High",IF(I14>=6,"Medium","Low"))) | K14: =IF(AND(MAX(D14:G14)=5,C14>=3,OR(J14="Low",J14="Medium")),"Yes","") | L14: =IF(K14="Yes","High",J14) | M14: 12 | N14: 10 | O14: =RANK(I14,$I$5:$I$20) | P14: One clinician's EHR access misused; limited record count | Q14: Denise Coleman
A15: R13 | B15: Workforce member views patient records without a care need (snooping) | C15: 3 | D15: 2 | E15: 1 | F15: 4 | G15: 4 | H15: =D15*'Criteria & Weights'!$H$6+E15*'Criteria & Weights'!$H$7+F15*'Criteria & Weights'!$H$8+G15*'Criteria & Weights'!$H$9 | I15: =C15*H15 | J15: =IF(I15>=20,"Critical",IF(I15>=12,"High",IF(I15>=6,"Medium","Low"))) | K15: =IF(AND(MAX(D15:G15)=5,C15>=3,OR(J15="Low",J15="Medium")),"Yes","") | L15: =IF(K15="Yes","High",J15) | M15: 12 | N15: 11 | O15: =RANK(I15,$I$5:$I$20) | P15: Snooping is the most common OCR complaint; strong patient-trust impact | Q15: Denise Coleman
A16: R16 | B16: Breach notification deadline missed (no Privacy Officer) | C16: 2 | D16: 3 | E16: 1 | F16: 5 | G16: 4 | H16: =D16*'Criteria & Weights'!$H$6+E16*'Criteria & Weights'!$H$7+F16*'Criteria & Weights'!$H$8+G16*'Criteria & Weights'!$H$9 | I16: =C16*H16 | J16: =IF(I16>=20,"Critical",IF(I16>=12,"High",IF(I16>=6,"Medium","Low"))) | K16: =IF(AND(MAX(D16:G16)=5,C16>=3,OR(J16="Low",J16="Medium")),"Yes","") | L16: =IF(K16="Yes","High",J16) | M16: 8 | N16: 15 | O16: =RANK(I16,$I$5:$I$20) | P16: Late notification is a separate §164.404 violation; public criticism | Q16: Denise Coleman
... A20: R07 | B20: Shared test account in production can read ePHI | C20: 2 | D20: 1 | E20: 1 | F20: 3 | G20: 2 | H20: =D20*'Criteria & Weights'!$H$6+E20*'Criteria & Weights'!$H$7+F20*'Criteria & Weights'!$H$8+G20*'Criteria & Weights'!$H$9 | I20: =C20*H20 | J20: =IF(I20>=20,"Critical",IF(I20>=12,"High",IF(I20>=6,"Medium","Low"))) | K20: =IF(AND(MAX(D20:G20)=5,C20>=3,OR(J20="Low",J20="Medium")),"Yes","") | L20: =IF(K20="Yes","High",J20) | M20: 6 | N20: 16 | O20: =RANK(I20,$I$5:$I$20) | P20: Untraceable ePHI read access violates unique-ID standard | Q20: Sabitha S Karanavar

Sheet BIA
A1: Business Impact Analysis — MTD, RTO, RPO
A2: Assumptions: 150-bed simulated hospital, $90,000,000 annual net patient revenue, $75/h labour. Yellow = inputs.
A3: Hourly patient revenue | B3: =90000000/8760
A5: System / process | B5: Owner | C5: Revenue share | D5: Extra labour $/h | E5: Other $/h | F5: Hourly impact | G5: One-time recovery | H5: Financial tolerance | I5: Hours to tolerance | J5: Patient-safety limit (h) | K5: Policy max (h) | L5: MTD (h) | M5: MTD driver | N5: Work recovery time (h) | O5: RTO ≤ MTD − WRT − 1 h | P5: RTO (tier) | Q5: Transactions/h | R5: Max re-entry | S5: RPO (h) | T5: Impact @1h | U5: Impact @4h | V5: Impact @8h | W5: Impact @24h | X5: Impact @72h | Y5: Criticality tier | Z5: Depends on
A6: EHR (clinical documentation & orders) | B6: Sarah Chen | C6: 0.6 | D6: 720 | E6: 0 | F6: =C6*$B$3+D6+E6 | G6: 25000 | H6: 150000 | I6: =H6/F6 | J6: 8 | K6: 72 | L6: =MIN(I6,K6,J6) | M6: patient-safety limit | N6: 3 | O6: =L6-N6-1 | P6: 4 | Q6: 400 | R6: 100 | S6: =R6/Q6 | T6: =G6+F6*1 | U6: =G6+F6*4 | V6: =G6+F6*8 | W6: =G6+F6*24 | X6: =G6+F6*72 | Y6: 1 | Z6: Entra ID, HVMC-Prod-VNet, hvmcehrstorage, LIS, Pharmacy System
A7: Laboratory Information System | B7: Elena Petrova | C7: 0.1 | D7: 300 | E7: 1200 | F7: =C7*$B$3+D7+E7 | G7: 8000 | H7: 60000 | I7: =H7/F7 | J7: 4 | K7: 72 | L7: =MIN(I7,K7,J7) | M7: patient-safety limit | N7: 1 | O7: =L7-N7-1 | P7: 2 | Q7: 120 | R7: 60 | S7: =R7/Q7 | T7: =G7+F7*1 | U7: =G7+F7*4 | V7: =G7+F7*8 | W7: =G7+F7*24 | X7: =G7+F7*72 | Y7: 1 | Z7: Entra ID, HVMC-Prod-VNet, EHR
A8: Pharmacy Management System | B8: David Patel | C8: 0.08 | D8: 360 | E8: 600 | F8: =C8*$B$3+D8+E8 | G8: 8000 | H8: 50000 | I8: =H8/F8 | J8: 6 | K8: 72 | L8: =MIN(I8,K8,J8) | M8: patient-safety limit | N8: 1 | O8: =L8-N8-1 | P8: 4 | Q8: 80 | R8: 20 | S8: =R8/Q8 | T8: =G8+F8*1 | U8: =G8+F8*4 | V8: =G8+F8*8 | W8: =G8+F8*24 | X8: =G8+F8*72 | Y8: 1 | Z8: Entra ID, HVMC-Prod-VNet, EHR
A9: Appointment Scheduling | B9: Grace Nguyen | C9: 0.05 | D9: 120 | E9: 0 | F9: =C9*$B$3+D9+E9 | G9: 3000 | H9: 40000 | I9: =H9/F9 | J9: — | K9: 72 | L9: =MIN(I9,K9) | M9: financial tolerance | N9: 4 | O9: =L9-N9-1 | P9: 48 | Q9: 30 | R9: 120 | S9: =R9/Q9 | T9: =G9+F9*1 | U9: =G9+F9*4 | V9: =G9+F9*8 | W9: =G9+F9*24 | X9: =G9+F9*72 | Y9: 3 | Z9: Entra ID, EHR
A10: Payroll | B10: Brian Adeyemi | C10: 0 | D10: 0 | E10: 150 | F10: =C10*$B$3+D10+E10 | G10: 2000 | H10: 20000 | I10: =H10/F10 | J10: — | K10: 72 | L10: =MIN(I10,K10) | M10: policy maximum | N10: 8 | O10: =L10-N10-1 | P10: 48 | Q10: 5 | R10: 40 | S10: =R10/Q10 | T10: =G10+F10*1 | U10: =G10+F10*4 | V10: =G10+F10*8 | W10: =G10+F10*24 | X10: =G10+F10*72 | Y10: 3 | Z10: Entra ID
A11: HR Portal | B11: Daniel Osei | C11: 0 | D11: 0 | E11: 100 | F11: =C11*$B$3+D11+E11 | G11: 2000 | H11: 20000 | I11: =H11/F11 | J11: — | K11: 72 | L11: =MIN(I11,K11) | M11: policy maximum | N11: 4 | O11: =L11-N11-1 | P11: 48 | Q11: 5 | R11: 120 | S11: =R11/Q11 | T11: =G11+F11*1 | U11: =G11+F11*4 | V11: =G11+F11*8 | W11: =G11+F11*24 | X11: =G11+F11*72 | Y11: 3 | Z11: Entra ID
A12: Security Monitoring Portal | B12: Denise Coleman | C12: 0 | D12: 0 | E12: 200 | F12: =C12*$B$3+D12+E12 | G12: 4000 | H12: 20000 | I12: =H12/F12 | J12: — | K12: 24 | L12: =MIN(I12,K12) | M12: policy maximum | N12: 2 | O12: =L12-N12-1 | P12: 12 | Q12: 50 | R12: 200 | S12: =R12/Q12 | T12: =G12+F12*1 | U12: =G12+F12*4 | V12: =G12+F12*8 | W12: =G12+F12*24 | X12: =G12+F12*72 | Y12: 2 | Z12: Entra ID, Log Analytics (not deployed)
A13: IT Administration Console | B13: Kevin O'Brien | C13: 0 | D13: 0 | E13: 250 | F13: =C13*$B$3+D13+E13 | G13: 4000 | H13: 30000 | I13: =H13/F13 | J13: — | K13: 24 | L13: =MIN(I13,K13) | M13: policy maximum | N13: 2 | O13: =L13-N13-1 | P13: 12 | Q13: 10 | R13: 40 | S13: =R13/Q13 | T13: =G13+F13*1 | U13: =G13+F13*4 | V13: =G13+F13*8 | W13: =G13+F13*24 | X13: =G13+F13*72 | Y13: 2 | Z13: Entra ID, HVMC-Bastion
A14: VPN Portal | B14: Kevin O'Brien | C14: 0 | D14: 0 | E14: 50 | F14: =C14*$B$3+D14+E14 | G14: 1000 | H14: 10000 | I14: =H14/F14 | J14: — | K14: 72 | L14: =MIN(I14,K14) | M14: policy maximum | N14: 1 | O14: =L14-N14-1 | P14: 48 | Q14: 2 | R14: 20 | S14: =R14/Q14 | T14: =G14+F14*1 | U14: =G14+F14*4 | V14: =G14+F14*8 | W14: =G14+F14*24 | X14: =G14+F14*72 | Y14: 3 | Z14: Entra ID
A17: Supporting services inherit the strictest requirement of the systems that depend on them
A18: Supporting service | B18: Owner | C18: Used by | D18: MTD (h) | E18: RTO (h) | F18: RPO | G18: Hourly impact if down
A19: Entra ID (identity) | B19: Sabitha S Karanavar | C19: All 9 systems | D19: 4 | E19: 2 | F19: 15 min | G19: 12577.397
A20: HVMC-Prod-VNet / LB / NAT | B20: Fatima Ali | C20: EHR, LIS, Pharmacy | D20: 4 | E20: 2 | F20: 15 min | G20: 11193.699
A21: hvmcehrstorage | B21: Sarah Chen | C21: EHR | D21: 8 | E21: 4 | F21: 15 min | G21: 6884.3836

Sheet Asset Exposure Register
A1: Critical Asset Risk Exposure Register
A2: Exposure = highest weighted risk score among linked risks · ALE from Risk Assessment Techniques (overlapping, not additive)
A4: Asset | B4: Type | C4: Owner | D4: BIA tier | E4: C | F4: I | G4: A | H4: Threat exposure (ATT&CK) | I4: Vulnerabilities (evidence) | J4: Linked risks | K4: Top risk | L4: Exposure score | M4: Exposure rating | N4: ALE of linked risks | O4: Depends on (upstream) | P4: Used by (downstream)
A5: hvmcehrstorage | B5: ePHI data store (Azure Storage) | C5: Sarah Chen | D5: 1 | E5: High | F5: High | G5: Mod | H5: T1530 Data from Cloud Storage, T1486 / T1485 Ransomware, Data Destruction, T1078 Valid Accounts (shared test account), T1105 Ingress Tool Transfer (malware) | I5: V02 public network access Enabled, firewall default Allow, shared-key access enabled; V05 blob versioning off, soft delete only 7 days, 0 resource locks, restore never tested; V07 Test Nurse - EHR holds HVMC-Nurse-EHR-ReadOnly on hvmcehrstorage; V11 all Defender for Cloud workload plans on Free tier; 0 security contacts configured | J5: R02, R05, R07, R11 | K5: R05 | L5: 14.01 | M5: High | N5: 1657775.7 | O5: Entra ID (RBAC), HVMC-Prod-VNet, Azure East US + paired region | P5: EHR, Nurse read-only role
A6: EHR application | B6: Clinical system | C6: Sarah Chen | D6: 1 | E6: High | F6: High | G6: High | H6: T1021 Remote Services (lateral movement), T1486 / T1485 Ransomware, Data Destruction, T1566 / T1557 Phishing, Adversary-in-the-Middle, Insider misuse (record snooping) | I6: V03 HVMC-Data-NSG has no deny rule; default AllowVnetInBound (65000) permits Web→Data on any port; V05 blob versioning off, soft delete only 7 days, 0 resource locks, restore never tested; V12 security defaults allow push/OTP MFA; no Conditional Access or phishing-resistant MFA; V13 no record-level access auditing or monthly access-log review | J6: R03, R05, R12, R13 | K6: R05 | L6: 14.01 | M6: High | N6: 1300272.8 | O6: Entra ID, Web/App/Data subnets, hvmcehrstorage | P6: Clinicians (12), LIS, Pharmacy, Scheduling
A7: HVMC-Prod-VNet — Data subnet | B7: Network segment 10.0.3.0/24 | C7: Fatima Ali | D7: 1 | E7: High | F7: High | G7: High | H7: T1021 Remote Services (lateral movement), Administrator error (deletion) | I7: V03 HVMC-Data-NSG has no deny rule; default AllowVnetInBound (65000) permits Web→Data on any port; V15 0 resource locks on the production resource group | J7: R03, R15 | K7: R03 | L7: 13.56 | M7: High | N7: — | O7: HVMC-Data-NSG, HVMC-CloudSecurity-RG | P7: EHR database (SQL 1433)
A8: Pharmacy Management System | B8: Clinical system | C8: David Patel | D8: 1 | E8: Mod | F8: High | G8: High | H8: T1021 Remote Services (lateral movement), Insider misuse (record snooping) | I8: V03 HVMC-Data-NSG has no deny rule; default AllowVnetInBound (65000) permits Web→Data on any port; V13 no record-level access auditing or monthly access-log review | J8: R03, R13 | K8: R03 | L8: 13.56 | M8: High | N8: 74960.293 | O8: Entra ID, network, EHR orders | P8: Pharmacists (3), nursing medication administration
A9: Entra ID tenant | B9: Identity platform (SaaS) | C9: Sabitha S Karanavar | D9: 1 | E9: High | F9: High | G9: High | H9: T1078.004 Valid Cloud Accounts (admin), T1078 Valid Accounts (third party), T1528 Steal Application Access Token, T1566 / T1557 Phishing, Adversary-in-the-Middle | I9: V04 1 Global Administrator, no break-glass account, same person is subscription Owner; V06 Carlos Diaz account has no expiry date; no business associate agreement on file; V08 any user can register apps and create tenants; guest invites allowed from everyone; V12 security defaults allow push/OTP MFA; no Conditional Access or phishing-resistant MFA | J9: R04, R06, R08, R12 | K9: R04 | L9: 9.72 | M9: Medium | N9: 168180.14 | O9: Microsoft cloud; one Global Admin account | P9: All 9 HVMC systems, Azure RBAC, VPN
A10: Laboratory Information System | B10: Clinical system | C10: Elena Petrova | D10: 1 | E10: Mod | F10: High | G10: Mod | H10: T1566 / T1557 Phishing, Adversary-in-the-Middle, Insider misuse (record snooping) | I10: V12 security defaults allow push/OTP MFA; no Conditional Access or phishing-resistant MFA; V13 no record-level access auditing or monthly access-log review | J10: R12, R13 | K10: R12 | L10: 8.91 | M10: Medium | N10: 243140.44 | O10: Entra ID, network, EHR order feed | P10: EHR (results), clinicians
A11: Security Monitoring Portal | B11: Security operations | C11: Denise Coleman | D11: 2 | E11: Mod | F11: High | G11: Mod | H11: T1562.008 Disable Cloud Logs, Process failure (late breach notice) | I11: V01 0 Log Analytics workspaces, 0 activity-log diagnostic settings, 0 alert rules, 0 NSG flow logs; V16 Privacy Officer role vacant | J11: R01, R16 | K11: R01 | L11: 16.64 | M11: High | N11: 864926.46 | O11: Entra ID, Log Analytics (not deployed) | P11: Incident response, HIPAA audit review
A12: IT Administration Console | B12: Privileged administration | C12: Kevin O'Brien | D12: 2 | E12: High | F12: High | G12: Mod | H12: T1078.004 Valid Cloud Accounts (admin), Administrator error (deletion) | I12: V04 1 Global Administrator, no break-glass account, same person is subscription Owner; V15 0 resource locks on the production resource group | J12: R04, R15 | K12: R04 | L12: 9.72 | M12: Medium | N12: — | O12: Entra ID, HVMC-Bastion | P12: All infrastructure changes
A13: Legacy public server | B13: Internet-facing host (lab scan target) | C13: Kevin O'Brien | D13: 3 | E13: Low | F13: Mod | G13: Low | H13: T1190 Exploit Public-Facing Application | I13: V09 decade-old OpenSSH with ssh-agent forwarding flaw; V10 Apache 2.4.7 with public exploits available | J13: R09, R10 | K13: R10 | L13: 12.76 | M13: High | N13: — | O13: Internet | P13: None (isolated)
A14: VPN Portal | B14: Remote access | C14: Kevin O'Brien | D14: 3 | E14: Mod | F14: Mod | G14: Mod | H14: T1078 Valid Accounts (third party) | I14: V06 Carlos Diaz account has no expiry date; no business associate agreement on file | J14: R06 | K14: R06 | L14: 4.6 | M14: Low | N14: — | O14: Entra ID | P14: Contractor (Carlos Diaz)
A15: HR Portal & Payroll | B15: Business systems | C15: Daniel Osei / Brian Adeyemi | D15: 3 | E15: Mod | F15: Mod | G15: Low | H15: Negligent insider | I15: V14 no sanction policy; HIPAA training completion not recorded | J15: R14 | K15: R14 | L15: 3.94 | M15: Low | N15: — | O15: Entra ID | P15: HR (2), Finance (2)

Sheet Approval
A1: Evaluation Criteria — Stakeholder Approval
A2: Simulated sign-off for the lab project. Replace with real signatures/dates if collected.
A4: Name | B4: Role | C4: Reviewed | D4: Approval role | E4: Decision | F4: Signature | G4: Date
A5: Denise Coleman | B5: Security Supervisor / HIPAA Security Officer | C5: Overall criteria, compliance scale | D5: Owner | E5: Approved (simulated) | G5: 2026-10-14
A6: Kevin O'Brien | B6: IT Manager / IT Risk Owner | C6: Operational scale, RTO/RPO feasibility | D6: Approver | E6: Approved (simulated) | G6: 2026-10-14
A7: Brian Adeyemi | B7: Finance Manager | C7: Financial scale, BIA cost assumptions | D7: Approver | E7: Approved (simulated) | G7: 2026-10-14
A8: Sarah Chen | B8: Physician, EHR Data Owner | C8: Patient-safety limits, clinical MTDs | D8: Approver | E8: Approved (simulated) | G8: 2026-10-14
A9: Elena Petrova | B9: Lab Manager, LIS Owner | C9: LIS MTD/RPO | D9: Reviewer | E9: Approved (simulated) | G9: 2026-10-14
A10: David Patel | B10: Pharmacist, Pharmacy System Owner | C10: Pharmacy MTD/RPO | D10: Reviewer | E10: Approved (simulated) | G10: 2026-10-14
A11: Executive Risk Committee | B11: CEO, CFO, CMO (not modeled in tenant) | C11: Final approval of weights and tolerances | D11: Final approver | E11: Approved (simulated) | G11: 2026-10-14
A13: Review cycle: annually, or after a major incident, new system, or change in regulation. Version history kept on this sheet.
A15: Version | B15: Date | C15: Change | D15: Approved by
A16: 1.0 | B16: 2026-10-14 | C16: Initial criteria, AHP weights, BIA tolerances | D16: Executive Risk Committee (simulated)
